lakedoc/__init__.py
lakedoc/assets/doc-type-default.svg
lakedoc/context/__init__.py
lakedoc/context/base.py
lakedoc/context/lake.py
lakedoc/context/mod.py
lakedoc/context/mod.pyi
lakedoc/converters/__init__.py
lakedoc/converters/base.py
lakedoc/converters/ht2md/__init__.py
lakedoc/converters/ht2md/converter.py
lakedoc/converters/ht2md/converter.pyi
lakedoc/converters/html_converter.py
lakedoc/converters/md_converter.py
lakedoc/converters/pdf_converter.py
lakedoc/utils/__init__.py
lakedoc/utils/debug.py
lakedoc/utils/errors.py
lakedoc/utils/file.py
lakedoc/utils/string.py
lakedoc-1.1.2.dist-info/licenses/LICENSE
lakedoc-1.1.2.dist-info/METADATA
lakedoc-1.1.2.dist-info/WHEEL
lakedoc-1.1.2.dist-info/RECORD
