Metadata-Version: 2.4
Name: lakedoc
Version: 1.1.2
Summary: Convert Lake documents (Yuque) into the specified format.
License-Expression: MIT
License-File: LICENSE
Author: gupingan
Author-email: gupingan6@outlook.com
Requires-Python: >=3.7
Classifier: Programming Language :: Python :: 3
Classifier: Programming Language :: Python :: 3.7
Classifier: Programming Language :: Python :: 3.8
Classifier: Programming Language :: Python :: 3.9
Classifier: Programming Language :: Python :: 3.10
Classifier: Programming Language :: Python :: 3.11
Classifier: Programming Language :: Python :: 3.12
Classifier: Programming Language :: Python :: 3.13
Classifier: Programming Language :: Python :: 3.14
Requires-Dist: beautifulsoup4 (==4.12.3)
Requires-Dist: colorama (==0.4.6)
Requires-Dist: markdown (==3.4.4)
Requires-Dist: pymdown-extensions (==10.0.1)
Project-URL: Documentation, https://github.com/gupingan/lakedoc
Project-URL: Homepage, https://github.com/gupingan/lakedoc
Project-URL: Repository, https://github.com/gupingan/lakedoc
